<oai_dc:dc xmlns:oai_dc="http://www.openarchives.org/OAI/2.0/oai_dc/" xmlns:dc="http://purl.org/dc/elements/1.1/" xmlns:xsi="http://www.w3.org/2001/XMLSchema-instance" xsi:schemaLocation="http://www.openarchives.org/OAI/2.0/oai_dc/ http://www.openarchives.org/OAI/2.0/oai_dc.xsd">
      <dc:title>Intellectual life in the Colonial South, 1585-1763 [electronic resource] /</dc:title>
      <dc:creator>Davis, Richard Beale.</dc:creator>
      <dc:type>text</dc:type>
      <dc:type>Electronic books</dc:type>
      <dc:publisher>Knoxville : University of Tennessee Press,</dc:publisher>
      <dc:date>c1978.</dc:date>
      <dc:language>eng</dc:language>
      <dc:description>Title of series taken from publisher's catalog.</dc:description>
      <dc:description>Includes bibliographical references and index.</dc:description>
      <dc:description/>
      <dc:description>Description based on print version record.</dc:description>
      <dc:description>Electronic reproduction.</dc:description>
      <dc:relation>Intellectual life in the Colonial South, 1585-1763.</dc:relation>
      <dc:identifier>http://www.newfoundpress.utk.edu/pubs/davis/</dc:identifier>
      <dc:identifier>URN:ISBN:0870492101 -- Canceled or invalid ISBN</dc:identifier>
      <dc:identifier>URN:ISBN:9780870492105 -- Canceled or invalid ISBN</dc:identifier>
   </oai_dc:dc>



